hey_bob/__init__.py
hey_bob/__main__.py
hey_bob/services.py
hey_bob/test.ipynb
hey_bob/data/lyrics.csv
hey_bob/data/lyrics.pickle
hey_bob-0.1.0.dist-info/METADATA
hey_bob-0.1.0.dist-info/WHEEL
hey_bob-0.1.0.dist-info/entry_points.txt
hey_bob-0.1.0.dist-info/RECORD
