Metadata-Version: 2.4
Name: hey-bob
Version: 0.1.0
Summary: Get extra inspiration by invoking random Bob Dylan lyrics.
Author-email: rafasacaan <rafasacaan@gmail.com>
Requires-Python: >=3.8
Requires-Dist: pandas>=2.0.3
